{"url":"http://127.0.0.1:3000/lab/query?component=query","text":"memgraph:7687\n| v3.10.1\n\n7.06 MiB\n827.25 MiB / 7.65 GiB\nmemgraph\nTransactional\n87\n213\n0\n0\n0\nAnonymous\n\nMENU\n\nQuery execution\nGraphChat\nShare history\nCollections\nQuery modules\nStreams\nGraph schema\nDatasets\nImport\nExport\nMonitoring\nData modeling\nSettings\nQuery execution\nCypher editor\nGraph Style editor\nParameters\n1\n2\nMATCH p=()-[]-()\nRETURN p;\nShare query\nRun query\n\nTo explore data and graph results run a query in the editor on top.\n\nEmpty view\nCombine your most needed views\n\nSometimes it’s just easier when you can see everything at once, so choose your view in the sidebar menu\n\nLab version 3.10.2\nLogs\nRun history","buttons":[{"i":0,"text":"Share query","aria":null,"title":""},{"i":1,"text":"Run query","aria":null,"title":""},{"i":2,"text":"Load default style","aria":null,"title":""},{"i":3,"text":"Load style","aria":null,"title":""},{"i":4,"text":" Save style ","aria":null,"title":""},{"i":5,"text":" Apply ","aria":null,"title":""},{"i":6,"text":" Share query ","aria":null,"title":""},{"i":7,"text":" Run query ","aria":null,"title":""}]}